byexample/__init__.py
byexample/byexample.py
byexample/cfg.py
byexample/cmdline.py
byexample/common.py
byexample/concern.py
byexample/concurrency.py
byexample/differ.py
byexample/example.py
byexample/executor.py
byexample/expected.py
byexample/finder.py
byexample/init.py
byexample/jobs.py
byexample/log.py
byexample/log_level.py
byexample/options.py
byexample/parser.py
byexample/parser_sm.py
byexample/prof.py
byexample/regex.py
byexample/runner.py
byexample/modules/__init__.py
byexample/modules/clipboard.py
byexample/modules/cond.py
byexample/modules/cpp.py
byexample/modules/delimiters.py
byexample/modules/elixir.py
byexample/modules/gdb.py
byexample/modules/go.py
byexample/modules/iasm.py
byexample/modules/java.py
byexample/modules/javascript.py
byexample/modules/php.py
byexample/modules/powershell.py
byexample/modules/progress.py
byexample/modules/python.py
byexample/modules/ruby.py
byexample/modules/rust.py
byexample/modules/shell.py
byexample/modules/gadgets/byexample-repl.js
byexample-10.5.6.data/data/LICENSE
byexample-10.5.6.dist-info/LICENSE
byexample-10.5.6.dist-info/METADATA
byexample-10.5.6.dist-info/WHEEL
byexample-10.5.6.dist-info/entry_points.txt
byexample-10.5.6.dist-info/top_level.txt
byexample-10.5.6.dist-info/RECORD
