Metadata-Version: 2.1
Name: byexample
Version: 10.5.6
Summary: Write snippets of code in C++, Python, Ruby, and others as documentation and execute them as regression tests.
Home-page: https://byexamples.github.io
Author: Di Paola Martin
Author-email: use-github-issues@example.com
License: GNU GPLv3
Keywords: doctest documentation test testing
Platform: UNKNOWN
Classifier: Development Status :: 5 - Production/Stable
Classifier: Intended Audience :: Developers
Classifier: Topic :: Documentation
Classifier: Topic :: Software Development :: Documentation
Classifier: Topic :: Software Development :: Testing
Classifier: License :: OSI Approved :: GNU General Public License v3 (GPLv3)
Classifier: Programming Language :: Python :: 2
Classifier: Programming Language :: Python :: 3
Classifier: Programming Language :: Python :: 2.7
Classifier: Programming Language :: Python :: 3.4
Classifier: Programming Language :: Python :: 3.5
Classifier: Programming Language :: Python :: 3.6
Classifier: Programming Language :: Python :: 3.7
Classifier: Programming Language :: Python :: 3.8
Classifier: Programming Language :: Python :: 3.9
Classifier: Programming Language :: Python :: 3.10
Classifier: Programming Language :: C
Classifier: Programming Language :: C++
Classifier: Programming Language :: JavaScript
Classifier: Programming Language :: Other
Classifier: Programming Language :: Other Scripting Engines
Classifier: Programming Language :: PHP
Classifier: Programming Language :: Ruby
Classifier: Programming Language :: Unix Shell
Requires-Python: >=3.6
Requires-Dist: appdirs (<2,>=1.4.3)
Requires-Dist: pexpect (<5,>=4)
Requires-Dist: pygments (<3,>=2)
Requires-Dist: pyte (<=0.8.1,>=0.8.0)
Requires-Dist: tqdm (<5,>=4)
